binder/postBuild
binder/requirements.txt
binder/runtime.txt
docs/Makefile
docs/make.bat
docs/requirements.txt
docs/src/citing.rst
docs/src/conf.py
docs/src/examples.rst
docs/src/getting_started.rst
docs/src/index.rst
docs/src/user_guide.rst
docs/src/_static/api.svg
docs/src/_static/banner.svg
docs/src/_static/contribute.svg
docs/src/_static/custom.js
docs/src/_static/logo.png
docs/src/_static/logo.svg
docs/src/_static/require.js
docs/src/_static/smol_cofe.svg
docs/src/_static/smol_moca.svg
docs/src/_static/smol_workflow.svg
docs/src/_static/starting.svg
docs/src/_static/user.svg
docs/src/_static/css/smol.css
docs/src/_templates/navbar-version.html
docs/src/api_reference/index.rst
docs/src/api_reference/io.rst
docs/src/api_reference/capp/generate.enumerate.rst
docs/src/api_reference/capp/generate.groundstate.rst
docs/src/api_reference/capp/generate.random.rst
docs/src/api_reference/capp/generate.rst
docs/src/api_reference/capp/generate.special.rst
docs/src/api_reference/capp/index.rst
docs/src/api_reference/cofe/clusterexpansion.rst
docs/src/api_reference/cofe/clusterspace.rst
docs/src/api_reference/cofe/extern.ewald.rst
docs/src/api_reference/cofe/index.rst
docs/src/api_reference/cofe/space.basis.rst
docs/src/api_reference/cofe/space.cluster.rst
docs/src/api_reference/cofe/space.domain.rst
docs/src/api_reference/cofe/space.orbit.rst
docs/src/api_reference/cofe/space.rst
docs/src/api_reference/cofe/wrangling.rst
docs/src/api_reference/cofe/wrangling.select.rst
docs/src/api_reference/cofe/wrangling.sw.rst
docs/src/api_reference/cofe/wrangling.tools.rst
docs/src/api_reference/moca/ensemble.rst
docs/src/api_reference/moca/index.rst
docs/src/api_reference/moca/kernel.bias.rst
docs/src/api_reference/moca/kernel.kernels.rst
docs/src/api_reference/moca/kernel.mcusher.rst
docs/src/api_reference/moca/kernel.rst
docs/src/api_reference/moca/processors.composite.rst
docs/src/api_reference/moca/processors.ewald.rst
docs/src/api_reference/moca/processors.expansion.rst
smol-0.5.3.dist-info/LICENSE
smol-0.5.3.dist-info/METADATA
smol-0.5.3.dist-info/WHEEL
smol-0.5.3.dist-info/top_level.txt
smol-0.5.3.dist-info/RECORD
