Metadata-Version: 2.1
Name: smol
Version: 0.5.3
Summary: Lighthweight but caffeinated Python implementation of computational methods for statistical mechanical calculations of configurational states in crystalline material systems.
Author-email: Luis Barroso-Luque <lbluque@berkeley.edu>, Fengyu Xie <lbluque@berkeley.edu>
Maintainer-email: Luis Barroso-Luque <lbluque@berkeley.edu>
License: ::
Project-URL: documentation, https://cedergrouphub.github.io/smol
Project-URL: repository, https://github.com/CederGroupHub/smol
Project-URL: changelog, https://cedergrouphub.github.io/smol/CHANGES.md
Project-URL: tracker, https://github.com/CederGroupHub/smol/issues
Classifier: Development Status :: 4 - Beta
Classifier: Programming Language :: Python :: 3 :: Only
Classifier: Programming Language :: Python :: 3.9
Classifier: Programming Language :: Python :: 3.10
Classifier: Programming Language :: Python :: 3.11
Classifier: Intended Audience :: Science/Research
Classifier: License :: OSI Approved :: BSD License
Classifier: Operating System :: OS Independent
Classifier: Topic :: Scientific/Engineering :: Physics
Classifier: Topic :: Scientific/Engineering :: Chemistry
Classifier: Topic :: Software Development :: Libraries :: Python Modules
Requires-Python: >=3.9
License-File: LICENSE
Requires-Dist: numpy>=1.24
Requires-Dist: pymatgen>=2023.08.10
Requires-Dist: monty>=v2022.9.8
Provides-Extra: optional
Requires-Dist: scikit-learn>=1.1.2; extra == "optional"
Requires-Dist: h5py>=3.6.0; extra == "optional"
Requires-Dist: polytope; extra == "optional"
Requires-Dist: cvxpy; extra == "optional"
Requires-Dist: cvxopt; extra == "optional"
Requires-Dist: gurobipy; extra == "optional"
Requires-Dist: pyscipopt; extra == "optional"
Provides-Extra: docs
Requires-Dist: sphinx>=7.0.0; extra == "docs"
Requires-Dist: pydata-sphinx-theme>=0.13.3; extra == "docs"
Requires-Dist: ipython>=8.2.0; extra == "docs"
Requires-Dist: nbsphinx>=0.9.0; extra == "docs"
Requires-Dist: nbsphinx-link>=1.3.0; extra == "docs"
Requires-Dist: sphinx-copybutton>=0.5.2; extra == "docs"
Requires-Dist: sphinx-autodoc-typehints>=1.24.0; extra == "docs"
Provides-Extra: test
Requires-Dist: pytest>=7.2.0; extra == "test"
Requires-Dist: pytest-cov>=4.0.0; extra == "test"
Requires-Dist: scikit-learn>=1.1.2; extra == "test"
Requires-Dist: h5py>=3.6.0; extra == "test"
Requires-Dist: coverage; extra == "test"
Requires-Dist: polytope; extra == "test"
Requires-Dist: cvxpy; extra == "test"
Requires-Dist: gurobipy; extra == "test"
Requires-Dist: pyscipopt; extra == "test"
Provides-Extra: dev
Requires-Dist: pre-commit>=2.12.1; extra == "dev"
Requires-Dist: flake8; extra == "dev"
Requires-Dist: pycodestyle; extra == "dev"
Requires-Dist: pydocstyle; extra == "dev"
Requires-Dist: pylint; extra == "dev"
Requires-Dist: black; extra == "dev"
Requires-Dist: isort; extra == "dev"
